lionweb/__init__.py
lionweb/lionweb_version.py
lionweb/py.typed
lionweb/api/__init__.py
lionweb/api/classifier_instance_resolver.py
lionweb/api/composite_classifier_instance_resolver.py
lionweb/api/local_classifier_instance_resolver.py
lionweb/api/unresolved_classifier_instance_exception.py
lionweb/client/__init__.py
lionweb/client/bulk_import.py
lionweb/client/client.py
lionweb/client/repository_archives.py
lionweb/generation/__init__.py
lionweb/generation/base_generator.py
lionweb/generation/configuration.py
lionweb/generation/deserializer_generation.py
lionweb/generation/generation_utils.py
lionweb/generation/generator.py
lionweb/generation/language_generation.py
lionweb/generation/naming_utils.py
lionweb/generation/node_classes_generation.py
lionweb/language/__init__.py
lionweb/language/annotation.py
lionweb/language/classifier.py
lionweb/language/concept.py
lionweb/language/containment.py
lionweb/language/data_type.py
lionweb/language/debug_utils.py
lionweb/language/definition.py
lionweb/language/enumeration.py
lionweb/language/enumeration_literal.py
lionweb/language/feature.py
lionweb/language/field.py
lionweb/language/ikeyed.py
lionweb/language/inamed.py
lionweb/language/interface.py
lionweb/language/language.py
lionweb/language/language_entity.py
lionweb/language/link.py
lionweb/language/lioncore_builtins.py
lionweb/language/namespace_provider.py
lionweb/language/namespaced_entity.py
lionweb/language/primitive_type.py
lionweb/language/property.py
lionweb/language/reference.py
lionweb/language/structured_data_type.py
lionweb/model/__init__.py
lionweb/model/annotation_instance.py
lionweb/model/classifier_instance.py
lionweb/model/classifier_instance_utils.py
lionweb/model/has_feature_values.py
lionweb/model/has_settable_parent.py
lionweb/model/node.py
lionweb/model/reference_value.py
lionweb/model/structured_data_type_instance.py
lionweb/model/structured_data_type_instance_utils.py
lionweb/model/impl/__init__.py
lionweb-0.4.0.dist-info/licenses/LICENSE.txt
lionweb-0.4.0.dist-info/METADATA
lionweb-0.4.0.dist-info/WHEEL
lionweb-0.4.0.dist-info/entry_points.txt
lionweb-0.4.0.dist-info/top_level.txt
lionweb-0.4.0.dist-info/RECORD
