Metadata-Version: 2.4
Name: lionweb
Version: 0.4.0
Summary: A Python package for working with LionWeb
Author-email: Federico Tomassetti <federico@strumenta.com>
License:                                  Apache License
Requires-Python: >=3.11
License-File: LICENSE.txt
Requires-Dist: requests
Requires-Dist: pydantic
Requires-Dist: typing_extensions>=4.8
Requires-Dist: protobuf
Requires-Dist: click
Requires-Dist: astor
Provides-Extra: dev
Requires-Dist: coverage; extra == "dev"
Requires-Dist: diff-cover; extra == "dev"
Requires-Dist: testcontainers>=4.0; extra == "dev"
Dynamic: license-file
